{"tossups": [{"question": ["automaton", "companion", "giants", "hero", "fleece", "khalkotauroi", "subject", "lost", "escape", "killed", "disorienting", "quest", "kyzikos", "rhodes", "mission", "river", "integral", "wedding", "sought", "night", "points", "epics", "man", "foiled", "wood", "plowed", "field", "keres", "argonauts", "firebreathing", "medea", "brought", "apollonius", "talking", "accidentally", "king", "love", "doliones", "dodona", "daughter", "city", "earthborn", "spirits", "hera", "taloss", "aietes", "attack", "hero", "valerius", "superhospitable", "10", "sandal", "disguised", "piece", "theseus", "(kayress)", "golden", "flaccus", "carrying", "beloved", "sixarmed"], "answer": "Jason [or Iason; do not accept \"Aison\"] &lt;Golfinos&gt;", "category": "Mythology"}, {"question": ["grand", "batu", "novgorod", "rus", "brothers", "vladimir", "killed", "river", "battle", "points", "(roos)", "princes", "duke", "wise", "tithes", "statue", "church", "ruled", "threw", "balcony", "built", "1240", "1240", "seized", "algirdas", "killing", "city", "baptized", "mongkes", "accursed", "christian", "church", "people", "khan", "city", "angering", "yaroslav", "sviatopolk", "perun", "envoys", "shortly", "attack", "served", "men", "10", "ukraine", "power", "blue", "waters", "sacked", "collapse", "crowded", "882", "aforementioned", "capital", "located"], "answer": "Kiev &lt;Cheyne&gt;", "subcategory": "European History", "category": "History"}, {"question": ["electron", "gain", "left", "steps", "step", "lattice", "constructing", "molar", "element", "energy", "points", "beryllium", "quantity", "difference", "anomalies", "enthalpy", "values", "chlorine", "period", "lattice", "ions", "carbon", "chemical", "halffilled", "onehalf", "exothermic", "quantity", "ionization", "negative", "condensation", "energy", "standard", "stability", "chloride", "hardness", "monatomic", "smaller", "approximated", "born\u2013haber", "potassium", "equal", "lithium", "increases", "nitrogen", "involving", "10", "gaseous", "filled", "cycle", "conferred", "orbitals", "elements"], "answer": "electron affinity [accept lattice energy or lattice enthalpy until read] &lt;Pendyala&gt;", "subcategory": "Chemistry", "category": "Science"}, {"question": ["produced", "seizure", "water", "wine", "painting", "suleiman", "commissioners", "points", "completed", "army", "veronese", "benedictine", "reallife", "musicians", "seated", "inspecting", "paolo", "copy", "turned", "tables", "digitally", "charles", "caliari", "napoleons", "event", "paintings", "person", "center", "alluding", "silence", "modeled", "contemporaries", "glass", "displayed", "jesus", "giorgio", "louvre", "code", "speaking", "artist", "san", "refectory", "benedetto", "magnificent", "10", "brother", "artists", "rulers", "venetian", "largest", "maggiore", "banquet", "hangs"], "answer": "The Wedding at Cana [or The Wedding Feast at Cana] &lt;Shimizu&gt;", "subcategory": "Visual Fine Arts", "category": "Fine Arts"}, {"question": ["55page", "centered", "author", "promoted", "behavior", "book", "1959", "cognitive", "expense", "suggested", "points", "newsweek", "required", "heard", "walden", "descartes", "feud", "review", "1971", "verbal", "lack", "innate", "defended", "punningly", "writer", "letter", "recalled", "kenneth", "syntactic", "men", "structures", "response", "question", "skill", "mens", "blanche", "language", "behaviorism", "paper", "missive", "learned", "ripped", "arose", "receiving", "men", "speech", "10", "1970", "answers", "linguist", "explaining", "maccorquodale", "journal", "psychology", "students", "scathing", "psychologist", "wrote", "locke"], "answer": "Burrhus Frederic Skinner AND Avram Noam Chomsky [accept in either order] &lt;Cheyne&gt;", "category": "Social Science"}, {"question": ["arrest", "king", "wonders", "soul", "creons", "ears", "edict", "asks", "recounts", "stabs", "lunges", "oedipus", "points", "prior", "man", "birds", "burial", "bride", "threatened", "rites", "play", "guard", "bribes", "sophocles", "cave", "declares", "title", "man", "character", "pain", "proper", "father", "accused", "screamed", "wonderful", "daughter", "hanged", "language", "discovering", "haemon", "torture", "clawed", "plays", "protagonist", "defies", "10", "play", "brother", "polynices", "lies", "chorus"], "answer": "Antigone &lt;Casalaspi&gt;", "subcategory": "Classical Literature", "category": "Literature"}, {"question": ["produced", "foreign", "winston", "attlee", "aneurin", "list", "directed", "beveridge", "eventual", "creation", "clement", "party", "points", "1945", "health", "chaired", "minister", "corrupt", "prime", "agent", "alleged", "wilson", "thought", "economist", "businessmen", "eyebrows", "spycatcher", "welsh", "conservatives", "book", "party", "orange", "member", "leading", "party", "national", "bevan", "peerages", "members", "lavender", "campaign", "political", "service", "group", "supposedly", "controversial", "harold", "report", "churchills", "10", "raised", "power", "including", "british", "clockwork"], "answer": "Labour Party &lt;Cheyne&gt;", "subcategory": "European History", "category": "History"}, {"question": ["longer", "smooth", "fasttwitch", "contract", "nmtype", "ryanodine", "precursor", "release", "nonglial", "receptor", "induce", "reticulum", "periods", "points", "plate", "myf5", "tissue", "differentiation", "fibers", "multinucleated", "promote", "nmjs", "cells", "ach", "muscle", "cardiac", "ion", "receptors", "produce", "fusion", "satellite", "fibers", "targets", "released", "repair", "mimetics", "tissue", "proliferation", "potentials", "cells", "respond", "controlled", "nicotinic", "striated", "1", "pancuronium", "curare", "depends", "type", "sarcoplasmic", "10", "mrf4", "voluntarily", "sites", "receptors", "slowtwitch", "quiescent", "ryr1", "primary"], "answer": "skeletal muscle [prompt on muscle or striated muscle] &lt;Smart&gt;", "subcategory": "Biology", "category": "Science"}, {"question": ["hank", "produced", "quinlan", "criminal", "plays", "cuckoo", "films", "memorialized", "notes", "dots", "role", "man", "1941", "corrupt", "points", "directed", "actor", "man", "reference", "early", "kind", "named", "harry", "based", "antagonists", "role", "word", "played", "actors", "enigmatically", "title", "william", "lime", "citizen", "lines", "character", "cop", "switzerlands", "dies", "touch", "people", "people", "ferris", "hearst", "evil", "clock", "refers", "man", "kane", "10", "matter", "democracy", "mans", "years", "film", "randolph", "wheel", "rosebud", "peace", "publisher"], "answer": "Orson Welles [or George Orson Welles] &lt;Cheyne&gt;", "category": "Trash"}, {"question": ["nathaniel", "written", "hanging", "land", "11th", "pneumonia", "monkey", "recounts", "maule", "young", "grinders", "points", "novels", "snow", "portrait", "history", "alice", "live", "drink", "god", "hawthorne", "characters", "daguerreotypist", "named", "tirelessly", "phoebe", "pyncheon", "chapter", "blood", "title", "holgrave", "central", "organ", "character", "death", "main", "wearing", "forces", "structure", "ancestor", "horrified", "afflicted", "haunts", "17thcentury", "judge", "arched", "performing", "matthew", "laborer", "hepzibah", "window", "girl", "evening", "gothic", "curse", "huge", "10", "search", "greed", "walk", "deed", "maine", "gown", "claim", "family"], "answer": "The House of the Seven Gables &lt;Belal&gt;", "subcategory": "American Literature", "category": "Literature"}, {"question": ["funded", "supported", "village", "koprowski", "safety", "dimes", "spreading", "points", "oconnor", "jr", "early", "labs", "thomas", "1956", "developed", "version", "drug", "opposed", "march", "eli", "university", "unprecedented", "oral", "defended", "tests", "1955", "jonas", "proclaimed", "cutter", "salk", "1950", "foundation", "basil", "michigan", "hilary", "lilly", "researcher", "children", "contaminated", "production", "success", "prevented", "company", "broadcast", "letchworth", "infectious", "sabin", "10", "albert", "effective", "work", "francis", "paralyzed", "form", "tested", "deaths", "disease"], "answer": "polio vaccine [or poliomyelitis vaccine; accept any answers about something that prevents polio] &lt;Cheyne&gt;", "subcategory": "American History", "category": "History"}, {"question": ["produced", "voltage", "study", "klitzing", "quantization", "cold", "levels", "remain", "introduced", "classical", "field", "points", "electrons", "discovered", "current", "fermions", "wavefunction", "esquared", "degenerate", "von", "free", "landau", "conductance", "transverse", "electric", "factors", "klaus", "applied", "fractional", "magnetic", "electrodynamics", "demonstrates", "laughlin", "levels", "dimensions", "confined", "integer", "temperatures", "integer", "varieties", "odd", "bfields", "filling", "composite", "terms", "analogous", "10", "strong", "occurs"], "answer": "quantum Hall effect [or fractional quantum Hall effect; or integer quantum Hall effect; prompt on Hall effect] &lt;Overman&gt;", "subcategory": "Physics", "category": "Science"}, {"question": ["users", "future", "king", "left", "believed", "crusaders", "slave", "mythical", "hoodoo", "sought", "defeat", "magi", "points", "muslims", "namesake", "descendant", "legendary", "legendarily", "devils", "india", "popular", "magic", "60", "title", "wife", "character", "homeland", "lilith", "day", "daughter", "african", "ruler", "ethiopia", "christian", "returned", "places", "sold", "acres", "10", "prince", "plow", "conqueror", "root", "kingdom", "prester", "devil", "held", "america", "renowned", "tasked", "wit", "helped"], "answer": "John [or John the Conqueror; or John de Conquer; or Prester John; prompt on Prester until read] &lt;Cheyne&gt;", "subcategory": "European History", "category": "History"}, {"question": ["event", "morning", "image", "planned", "twitter", "reynolds", "set", "photographs", "points", "20", "man", "moving", "phrase", "exhibition", "kind", "2017", "facts", "interior", "defiantly", "shia", "united", "originated", "multiyear", "produce", "event", "performance", "45th", "shut", "accusations", "turner", "president", "museum", "alternative", "art", "lebeouf", "team", "nastja", "assertion", "agencies", "term", "sade", "day", "sean", "ronkko", "luke", "department", "account", "officially", "coining", "spicers", "featured", "discussions", "untrue", "10", "michael", "marked", "told", "largest", "january", "america", "rogue", "event", "audience"], "answer": "the inauguration of Donald Trump &lt;Cheyne&gt;", "subcategory": "Current Events", "category": "Current Events"}, {"question": ["drinking", "moonlight", "waits", "stockings", "late", "grown", "author", "grievance", "observes", "points", "poems", "clear", "wife", "soaks", "ezra", "thoughts", "lifting", "notes", "letter", "rivermerchants", "deep", "aristocratic", "night", "unfaithful", "gauze", "paired", "speaker", "lover", "called", "yellow", "short", "mosses", "bright", "tang", "poet", "moon", "dew", "quiet", "lowering", "translated", "head", "pound", "august", "10", "butterflies", "poem", "watch", "dream", "stairs", "gate", "mans", "dynasty", "jewel", "including", "wrote"], "answer": "Li Bai [or Li Bo; or Li Po; or Rihaku] &lt;Casalaspi&gt;", "subcategory": "World Literature", "category": "Literature"}, {"question": ["intended", "iteration", "event", "1995", "objected", "organized", "ramzi", "iteration", "thenrecord", "2008", "international", "young", "viewed", "nations", "expressed", "points", "plot", "rock", "gathered", "park", "event", "bojinka", "attendees", "millions", "typically", "catholic", "number", "church", "people", "sort", "festival", "sydney", "place", "luneta", "panama", "yousefs", "racecourse", "krakow", "featured", "religious", "2019", "1995", "runs", "dismay", "10", "randwick", "years", "held", "2016", "running", "leader", "largest", "crowded", "poland", "event", "benedict", "assassinate", "pope"], "answer": "World Youth Day [or WYD] &lt;Cheyne&gt;", "subcategory": "Other History", "category": "History"}, {"question": ["emphasized", "produced", "caning", "punishments", "penalty", "1993", "europeans", "kuan", "banned", "magazine", "wired", "points", "fay", "death", "selfrighteous", "prime", "southern", "penalty", "article", "gibson", "knowitall", "committing", "posters", "leadership", "american", "william", "disneyland", "1970s", "rational", "calling", "parents", "leaders", "minister", "telling", "yew", "nair", "people", "sane", "harsh", "moments", "reassured", "faced", "sued", "numerous", "anguish", "children", "devan", "peninsula", "lee", "malaysian", "10", "michael", "vandalism", "corporal", "leader", "colleague", "country"], "answer": "Republic of Singapore &lt;Cheyne&gt;", "subcategory": "World History", "category": "History"}, {"question": ["rings", "eflat", "quoted", "marches", "plays", "melbourne", "(yohan", "includes", "lincolnshire", "seventeen", "posy", "poachers", "grainger", "movement", "stars", "sixmovement", "points", "dives", "lord", "percy", "suites", "vaughan", "sunday", "dargason", "john", "fantasia", "ensemble", "lazarus", "johan", "mays)", "williams", "songs", "folk", "called", "ensemble", "composed", "rufford", "sousa", "symphony", "meijs", "stripes", "ralph", "movements", "ensemble", "large", "type", "10", "originally", "suite", "piece", "led", "string", "philip", "park", "holst", "generally", "gustav"], "answer": "concert band [or military band; or symphonic band; or marching band; or wind band; or wind ensemble] &lt;Magin&gt;", "subcategory": "Auditory Fine Arts", "category": "Fine Arts"}, {"question": ["buried", "companion", "final", "asks", "start", "beckett", "sea", "points", "dog", "pulls", "man", "reveal", "live", "characters", "named", "faces", "lament", "play", "dirt", "hamm", "stand", "land", "rat", "mobility", "title", "character", "main", "culminates", "repeatedly", "samuel", "inability", "sit", "kiss", "dustbins", "interrupted", "plays", "refers", "toy", "10", "animal", "play", "curtains", "kill", "head", "chess", "exterminated", "dog", "clov", "strike", "characters", "match", "claims", "window"], "answer": "Endgame [or Fin de partie] &lt;Droge&gt;", "subcategory": "British Literature", "category": "Literature"}, {"question": ["addition", "planet", "believed", "compounds", "size", "parent", "mutual", "includes", "stripped", "moons", "pole", "scientists", "points", "announced", "locked", "gallifrey", "north", "organic", "macross", "bodys", "reason", "mordor", "identify", "macromolecules", "called", "chasma", "composed", "northwest\u2013southeast", "tholins", "transferred", "origin", "barycenter", "body", "formed", "status", "body", "moat", "mountain", "socalled", "area", "serenity", "chasma", "(kazmuh)", "dark", "bisects", "large", "pluto", "orbit", "unknown", "moon", "cap", "10", "macula", "2016", "reaction", "largest", "gravitationally", "informally", "tardis", "canyons"], "answer": "Charon &lt;Thompson&gt;", "subcategory": "Other Science", "category": "Science"}, {"question": ["jacobian", "defined", "change", "group", "formulas", "reduced", "derived", "general", "row", "echelon", "basis", "integrals", "times", "calculus", "objects", "symplectic", "berezinian", "points", "hessian", "objects", "test", "representation", "analogue", "operation", "form", "elements", "operations", "compute", "examples", "expansion", "identify", "derivative", "acting", "cofactor", "evaluate", "group", "twodimensional", "numbers", "arrays", "elementary", "super", "theory", "determinants", "10", "linear", "correspondence", "form", "elements", "multivariable"], "answer": "matrices [or matrix] &lt;Thompson&gt;", "subcategory": "Math", "category": "Science"}], "bonuses": [{"leadin": ["worlds", "graceland", "holding", "missouri", "forge", "kansas", "museum", "nylon", "dollywood", "weighs", "distinction", "17000", "pounds", "parton", "ball", "dolly", "southern", "object", "estate", "trap", "presleys", "pigeon", "massive", "citys", "tourist", "johnson", "created", "eastern", "museum", "replica", "oddball", "city", "cawker", "minnesota", "points", "supposedly", "claimed", "elvis", "darwin", "titanic", "10", "ripleys", "twine", "property", "dixie", "attractions", "city", "partons", "francis", "stampede", "including", "largest", "memphis", "located"], "answers": ["world's biggest ball of twine [or largest ball of twine]", "Branson, Missouri", "Tennessee &lt;Cheyne&gt;"], "parts": ["What distinction is claimed by various oddball tourist attractions, including an object located in Cawker City, Kansas, and one in Darwin, Minnesota, that weighs over 17,000 pounds?", "The world's largest nylon twine ball is located in this city's Ripley's Believe It or Not Museum. Dolly Parton's Dixie Stampede and a massive Titanic replica and museum are found in this tourist trap in southern Missouri.", "Another Titanic museum and a different Dolly Parton property, Dollywood, are also found in this state's eastern city of Pigeon Forge. Elvis Presley's estate of Graceland is located on the other side of this state, in Memphis."], "category": "Geography"}, {"leadin": ["dollars", "affairs", "prison", "bob", "1998", "candidacy", "perceived", "sexual", "1978", "livingston", "2016", "challenge", "unflattering", "hypocrisy", "man", "republicans", "attempts", "shot", "permanently", "offered", "produce", "molested", "president", "impeach", "wrestling", "position", "harm", "speaker", "paralyzed", "affair", "attempt", "position", "points", "coach", "republicans", "revelation", "working", "affair", "sentenced", "10", "revelations", "withdrew", "felt", "stories", "boys", "sexually"], "answers": ["Speaker of the House of Representatives", "William Jefferson \"Bill\" Clinton [or William Jefferson Blythe III]", "Larry Flynt Jr. &lt;Cheyne&gt;"], "parts": ["Name this position. The man who obtained it after Livingston withdrew was himself sentenced to prison in 2016 after revelations that he had sexually molested boys while working as a wrestling coach.", "Livingston said he withdrew his candidacy to be Speaker because he felt the revelation of his affair would harm attempts by the Republicans to impeach this President noted for his own sexual affairs.", "In an attempt to challenge what he perceived as hypocrisy, this man offered one million dollars to anyone who could produce unflattering sexual stories about the Republicans. He was shot in 1978 and is now permanently paralyzed."], "subcategory": "American History", "category": "History"}, {"leadin": ["cloud", "abandoned", "controversial", "girl", "random", "desires", "shut", "program", "darius", "chicago", "cordero", "authors", "ethnicity", "arizona", "latina", "sandra", "characters", "10", "author", "sally", "ethnicity", "friend", "cisneros", "esperanza", "studies", "minor", "sky", "assaulted", "coming", "escape", "literature", "location", "include", "controversially", "mango", "american", "age", "god", "writer", "house", "tucson", "sexually", "events", "passage", "street", "title", "claims", "points"], "answers": ["The House on Mango Street", "Mexican-American [or Chicana; or Chicano; prompt on Latina or Latino; prompt on Hispanic]", "carnival [prompt on festival; do not accept \"circus\"] &lt;Droge&gt;"], "parts": ["Name this coming of age novel about Esperanza Cordero, a Latina girl who desires to escape the title location in Chicago.", "The author of The House on Mango Street, Sandra Cisneros, is an American writer of this ethnicity. A program that studies the literature of authors of this ethnicity was controversially shut down in Tucson, Arizona.", "In a controversial passage in The House on Mango Street, Esperanza is abandoned by her friend Sally and sexually assaulted during one of these events."], "subcategory": "American Literature", "category": "Literature"}, {"leadin": ["(juhklopturus)", "paleozoic", "arthropod", "inches", "arachnidlike", "10", "shale", "named", "rex<em>", "discovered", "remipes", "organisms", "fossil", "jaekelopterus", "mass", "burgess", "arthropods", "extinct", "york", "trilobites", "long", "fossils", "extinction", "period", "27", "<em>isotelus", "period", "(yooriptuhrids)", "largest", "animals", "eightfootlong", "marine", "organisms", "died", "sections", "eurypterids", "measuring", "points"], "answers": ["trilobites [or Trilobita]", "sea scorpions [or Eurypterids; or Eurypterida]", "Permian period [prompt on Great Dying] &lt;Fulgenzi&gt;"], "parts": ["Name these Paleozoic arthropods found in the Burgess Shale that are often used as index fossils. They are named for having three sections.", "The largest known arthropod is Jaekelopterus (juh-KLOP-tur-us), an extinct eight-foot-long one of these marine organisms. E. remipes, one of these arachnid-like animals, is the state fossil of New York.", "Both trilobites and eurypterids (yoo-RIP-tuh-rids) died out at the end of this period. The largest mass extinction is named for this period and the following period."], "subcategory": "Other Science", "category": "Science"}, {"leadin": ["performs", "roberts", "book", "meaning", "protagonist", "family", "activity", "heinrich", "bolls", "beast", "man", "reallife", "army", "opposed", "built", "cake", "appealing", "robert", "refused", "party", "eats", "destroyed", "930", "hotel", "building", "key", "modeled", "sees", "german", "faehmel", "heinrich", "political", "billiards", "converted", "halfpast", "image", "points", "structure", "figures", "prince", "father", "war", "host", "10", "serving", "impulse", "weekday", "momentary", "authors", "ii", "partially"], "answers": ["playing billiards [or a cue sport]", "the Nazi party [or the National Socialist German Workers' Party; or the NSDAP]", "Saint Anthony's Abbey &lt;Cheyne&gt;"], "parts": ["Name this activity that Robert Faehmel performs each weekday beginning at 9:30 in the Prince Heinrich Hotel. Faehmel is the protagonist of a German author's novel.", "Robert Faehmel is the protagonist of Heinrich Boll's Billiards at Half-Past Nine. In the book, Robert refused to take \"the Host of the Beast,\" meaning he opposed this real-life political party.", "A key image in the novel is that of this structure, which was built by Robert's father, Heinrich, and then destroyed by Robert while serving in the army during World War II. At the end of the novel, the family eats from a cake modeled after this building."], "subcategory": "European Literature", "category": "Literature"}, {"leadin": ["juristic", "firm", "support", "534", "produced", "writings", "married", "implemented", "code", "issued", "emperor", "theodora", "ruler", "529", "10", "ruler", "corpus", "great", "sophia", "directed", "institutes", "tribonian", "byzantine", "work", "supervised", "ecloga", "parts", "digest", "original", "collection", "reign", "construction", "legal", "hagia", "codex", "project", "isaurian", "laws", "iconoclasm", "points"], "answers": ["Corpus Juris Civilis [prompt on partial answers; prompt on but DO NOT REVEAL Code of Justinian]", "Justinian I", "Leo III &lt;Cheyne&gt;"], "parts": ["Name this collection of laws and juristic writings issued from 529 to 534 by a certain emperor. The project that produced this work was directed by Tribonian.", "The Corpus was produced during the reign of this Byzantine ruler known as the \"Great,\" who was married to Theodora and supervised the construction of the Hagia Sophia.", "A new legal code, the \"Ecloga,\" was later implemented by this Byzantine ruler, who was known as the Isaurian and noted for his firm support of iconoclasm."], "subcategory": "European History", "category": "History"}, {"leadin": ["jr", "1938", "author", "legs", "antiwar", "face", "party", "hollywood", "hometown", "lester", "man", "blacklist", "protagonist", "cole", "victim", "filmmakers", "bonham", "refused", "member", "joe", "trumbo", "working", "screenwriter", "basis", "<em>eclipse<em>", "members", "fighting", "arms", "representatives", "group", "setting", "loses", "prevented", "points", "trumbo", "1947", "ring", "lardner", "testify", "war", "10", "included", "suspected", "blacklisted", "house"], "answers": ["Dalton Trumbo [or James Dalton Trumbo]", "Communist Party USA [or CPUSA]", "Hollywood Ten &lt;Cheyne&gt;"], "parts": ["Name this author of a 1938 anti-war novel in which the protagonist, Joe Bonham, loses his arms, legs, and face while fighting in World War I.", "After becoming a screenwriter, Trumbo was a victim of the Hollywood blacklist that prevented members, former members, or those suspected of being a member of this party from working.", "This group of filmmakers, which included Trumbo, Ring Lardner Jr., and Lester Cole, was blacklisted after they refused to testify before the House of Representatives in 1947."], "subcategory": "American Literature", "category": "Literature"}, {"leadin": ["enclosing", "defined", "polynomials", "describes", "time", "set", "function", "volumes", "points", "maximal", "namesake", "khachiyan", "polynomial", "programs", "developed", "extrema", "method", "guarantees", "refer", "decrease", "calculus", "shapes", "smallest", "rank", "derivative", "convex", "maxima", "term", "identify", "lie", "equal", "gauss\u2013lucas", "critical", "points", "leonid", "works", "solved", "(lookah)", "roots", "10", "theorem", "points", "respect", "candidates", "endpoints", "exist", "jacobian", "linear", "points", "0"], "answers": ["critical points", "convex hull", "ellipsoid method [or ellipsoid algorithm] &lt;Thompson&gt;"], "parts": ["Identify this term from calculus that is used to describe points where the derivative is equal to zero, and sometimes also to refer to endpoints and points where the derivative does not exist. Points described by this term are candidates for extrema.", "The Gauss\u2013Lucas (loo-KAH) theorem guarantees that the critical points of a polynomial function lie inside this set with respect to the polynomial's roots. Given any set of points, this set is defined as the smallest convex set containing all of the points.", "This method developed by Leonid Khachiyan was used to show that linear programs could be solved in polynomial time. It works by enclosing the maxima inside its namesake shapes as their volumes decrease to 0."], "subcategory": "Math", "category": "Science"}, {"leadin": ["day", "ashkenazi", "kippur", "holiday", "sandy", "god", "kippur", "judaism", "year", "holy", "burial", "yom", "1965", "recited", "game", "days", "declaration", "series", "holiest", "annulment", "rosh", "white", "vows", "day", "period", "hashanah", "1", "jews", "atonement", "points", "robe", "refers", "completes", "linen", "playing", "married", "evening", "men", "10", "observed", "service", "synagogue", "koufax", "personal", "high", "oaths", "wear", "robe", "serve"], "answers": ["Yom Kippur", "Kol Nidrei", "kittel [or sargenes] &lt;Cheyne&gt;"], "parts": ["Name this holiest day of the year in Judaism, the Day of Atonement that completes the period of the High Holy Days that begins with Rosh Hashanah.", "At the beginning of the evening service on Yom Kippur, this declaration is recited in the synagogue. Its name means \"all vows,\" which refers to its annulment of all personal oaths made to God.", "Ashkenazi Jews who are married men wear this white linen robe on Yom Kippur. It can also serve as a burial robe."], "category": "Religion"}, {"leadin": ["arm\u00e9", "musical", "guillaume", "heavy", "chamber", "quodlibet", "sera", "busnois", "scholars", "centuries", "lingua", "johann", "fay", "cantus", "pour", "(zheeg)", "15th", "imitative", "popular", "tune", "based", "super", "major", "missa", "(boonwah)", "mensuration", "paired", "firmus", "vous<em>", "antoine", "francoflemish", "arm\u00e9", "pachelbel", "mass", "16th", "gigue", "write", "disagree", "technique", "melody", "points", "tune", "lhomme", "type", "lhomme", "10", "<em>il", "pange", "piece", "secular", "masses", "du", "titles", "voces", "musicales", "josquins", "composer"], "answers": ["\"L'homme arm\u00e9\" (lum ar-MAY) [or \"The Armed Man\"]", "Josquin des Prez (joe-SCAN deh PRAY) [prompt on des Prez]", "canon &lt;White&gt;"], "parts": ["Name this secular tune popular in the 15th and 16th centuries. Scholars disagree as to whether Busnois or Guillaume du Fay was the first composer to write a cantus firmus mass based on this tune.", "This Franco-Flemish composer of the Missa pange lingua is best known for his two masses based on the \"L'homme arm\u00e9\" melody.", "Josquin's Missa l'homme arm\u00e9 super voces musicales makes heavy use of the mensuration type of this imitative musical technique. It titles a D major chamber piece that Johann Pachelbel paired with a gigue (zheeg)."], "subcategory": "Auditory Fine Arts", "category": "Fine Arts"}, {"leadin": ["panel", "produced", "founded", "hofmann", "convulsive", "middle", "symptoms", "spreads", "chemical", "thiol", "controversially", "deaths", "element", "anthonys", "cias", "responsible", "grainrelated", "commissioned", "ergotamine", "treat", "salem", "drug", "caused", "element", "20thcentury", "vaccine", "behavior", "mkultra", "saint", "called", "rye", "incorrectly", "symptoms", "administered", "ergotisms", "depicts", "project", "disease", "order", "supposed", "<em>isenheim", "group", "autism", "rate", "points", "fungusinfected", "claimed", "witches", "increased", "preservative", "10", "albert", "bonds", "monastic", "fungicides", "altarpiece<em>", "ergotism", "sufferer", "hallucinogenic", "ages", "disease"], "answers": ["ergotism", "LSD [or lysergic acid diethylamide; or acid]", "mercury [or Hg] &lt;Shimizu&gt;"], "parts": ["Name this disease that spreads through fungus-infected rye and was often called \"Saint Anthony's fire\" during the Middle Ages. It may have been responsible for the behavior of the supposed Salem witches, since many of its symptoms are convulsive.", "This hallucinogenic drug was first produced by Albert Hofmann from ergotamine, the chemical that causes ergotism's symptoms. It was controversially administered as part of the CIA's Project MKUltra.", "Various 20th-century grain-related deaths were caused not by ergotism, but by fungicides containing this element. A vaccine preservative in which this element bonds with a thiol group was incorrectly claimed to have caused an increased rate of autism."], "subcategory": "Biology", "category": "Science"}, {"leadin": ["believed", "kings", "hellenistic", "schliemann", "man", "process", "vault", "schliemann", "mythical", "namesake", "island", "thought", "named", "happened", "refer", "sons", "writer", "events", "war", "achaeans", "priam", "agamemnons", "killing", "figures", "assumes", "mythography", "feeding", "people", "mortal", "indian", "term", "inscription", "heinrich", "gods", "city", "euhemerists", "approach", "points", "famous", "claimed", "cursed", "ocean", "evidence", "10", "ruins", "mycenae", "brother", "led", "historical", "tomb", "dynasty", "hisarlik", "bases", "thyestess", "father", "revealing", "mythical"], "answers": ["euhemerism (yoo-HEM-er-ism) [accept word forms; do not accept \"deification\"]", "The Trojan War [accept Troy, Troia, Ilion, or Ilium for \"Trojan\"]", "Atreus &lt;Golfinos&gt;"], "parts": ["Give this term for an approach to mythography that assumes or tries to find historical bases for mythical people and events. It can also refer to the process by which historical figures become mythical.", "One of the most famous euhemerists, Heinrich Schliemann, believed ruins at Hisarlik to be evidence that this war between the Achaeans and a city led by Priam actually happened.", "Schliemann thought a \"vault\" near Mycenae was the tomb of this man, Agamemnon's father. He cursed his namesake dynasty by killing his brother Thyestes's sons and feeding them to him."], "category": "Mythology"}, {"leadin": ["kingdom", "2009", "amis", "closed", "hawk", "ends", "poetry", "missed", "april", "collections", "notes", "values<em>", "<em>family", "hope", "sense", "cruelest", "man", "1998", "post", "limerick", "united", "favorite", "", "stating", "title", "ann", "poet", "duffy", "death", "love", "carol", "2011", "laureate", "include", "poet", "rain", "1984", "contemporary", "group", "letters", "honor", "knew", "points", "title", "english", "eliot", "10", "poem", "limericks", "making", "wouldnt", "summarizing", "held", "collection", "youll", "birthday", "cope", "kingsley", "cocoa", "uks", "month"], "answers": ["Wendy Cope", "The Waste Land", "Edward \"Ted\" Hughes &lt;Collins&gt;"], "parts": ["Name this contemporary English poet who closed her collection Making Cocoa for Kingsley Amis with the title poem stating, \"I knew it wouldn't be much of a poem / But I love the title.\"", "Making Cocoa for Kingsley Amis contains a group of limericks summarizing this T.\u00a0S. Eliot poem beginning \"April is the cruelest month.\" The last limerick ends, \"I hope you'll make sense of the notes.\"", "Cope had previously missed out at becoming the UK's Poet Laureate in 1998, after the death of this man who had held the post from 1984. His poetry collections include The Hawk in the Rain and Birthday Letters."], "subcategory": "British Literature", "category": "Literature"}, {"leadin": ["history", "discontent", "wife", "response", "receive", "1810", "accused", "question", "attacked", "1817", "man", "10", "author", "caroline", "england", "theory", "publicly", "brunswick", "chartism", "people", "1839", "raised", "promoted", "mans", "carriage", "passed", "pamphlet", "popular", "question", "adultery", "trial", "chronicle", "relief", "great", "rise", "workhouses", "french", "january", "condition", "1834", "answer", "allowed", "wrote", "parliament", "laws", "revolution", "points"], "answers": ["Thomas Carlyle", "George IV [prompt on George]", "Poor Laws &lt;Magin&gt;"], "parts": ["This author raised the \"Condition of England\" Question in his 1839 pamphlet \"Chartism.\" He promoted the \"great man\" theory of history and wrote a popular chronicle of the French Revolution.", "As part of the discontent giving rise to the \"Condition of England\" Question, this man's carriage was attacked in January 1817. In 1810, he publicly accused his wife, Caroline of Brunswick, of adultery and put her on trial.", "In response to the \"Condition of England\" Question, Parliament passed one of these laws in 1834 that only allowed people to receive relief from workhouses."], "subcategory": "European History", "category": "History"}, {"leadin": ["features", "close", "atwood", "chaotic", "double", "perioddoubling", "pendulum", "conditions", "function", "namesake", "exhibit", "quantity", "oseledetss", "named", "displays", "dynamical", "russian", "property", "behavior", "theorem", "sensitivity", "systems", "trajectories", "swinging", "displayed", "pitchfork", "butterfly", "varieties", "initial", "machine", "plots", "rate", "points", "property", "parameter", "divergence", "extreme", "systems", "attractor", "10", "mathematician", "positive", "diagrams", "represents", "determined"], "answers": ["chaos [accept word forms]", "bifurcation diagram", "Lyapunov exponent [prompt on partial answer] &lt;Rombro&gt;"], "parts": ["Name this property of a dynamical system that displays extreme sensitivity to initial conditions. The swinging Atwood machine and the double pendulum both have this property.", "The behavior of chaotic systems can be displayed on one of these plots, which show the value of the attractor as a function of a namesake parameter. The features displayed on these diagrams can be of the pitchfork or period-doubling varieties.", "For a chaotic system, the value of this quantity, which represents the rate of divergence of close trajectories, is positive. This value, which can be determined using Oseledets's theorem, is named for a Russian mathematician."], "subcategory": "Physics", "category": "Science"}, {"leadin": ["genius", "education", "dutchman", "character", "person", "written", "accompanied", "claimed", "peter", "prince", "reallife", "army", "guardian", "plots", "prince", "ii", "10", "author", "prince", "dialogue", "heaven", "christian", "loved", "opposed", "barred", "excluded", "ruling", "saint", "heaven", "conquer", "invade", "philosophical", "argues", "angel", "dialogue", "julius", "heaven", "erasmuss", "feared", "title", "points"], "answers": ["Julius II [or Giulio II; or Giuliano della Rovere]", "Erasmus of Rotterdam [or Desiderius Erasmus Roterodamus]", "Niccol\u00f2 Machiavelli [or Niccol\u00f2 di Bernardo dei Machiavelli] &lt;Cheyne&gt;"], "parts": ["Name this real-life person who, in a philosophical dialogue, is barred from heaven by Saint Peter. This character then plots to use an army to invade and conquer heaven.", "Julius II is the title character of the dialogue Julius Excluded from Heaven, which was written by this Dutchman, the author of Education of a Christian Prince.", "In Erasmus's Education of a Christian Prince, he argues that a ruling prince should be loved, as opposed to this author of The Prince, who claimed it was better for a prince to be feared."], "category": "Literature"}, {"leadin": ["speaker", "market", "king", "written", "exclaims", "love", "elemental", "type", "ocean", "10", "despair", "animal", "poem", "odes", "flights", "describes", "notes", "nerudas", "refrain", "chilean", "vegetables", "song", "desire", "wars", "includes", "terrible", "sank", "memory", "poem", "poet", "poems", "catafalqued", "accumulated", "night", "emerges", "points"], "answers": ["\"A Song of Despair\" [or \"Una Canci\u00f3n Desesperada\"]", "Pablo Neruda [or Neftali Ricardo Reyes Basoalto]", "a large tuna in the market [or un gran at\u00fan en el mercado; prompt on fish] &lt;Fulgenzi&gt;"], "parts": ["Name this poem that begins, \"The memory of you emerges from the night around me,\" and includes the refrain, \"In you everything sank!\"", "Twenty Love Poems and a Song of Despair was written by this Chilean poet.", "One of Neruda's Elemental Odes describes this type of animal \"among the market vegetables,\" whom he describes as the \"catafalqued king of my own ocean.\""], "subcategory": "World Literature", "category": "Literature"}, {"leadin": ["harrisons", "namesake", "1960", "sitin", "department", "tallest", "woolworth", "organ", "building", "founded", "man", "city", "flagship", "store", "served", "huge", "store", "10", "building", "twelvestory", "greensboro", "benjamin", "fiveanddime", "atrium", "united", "philadelphia", "day", "north", "1913", "originated", "innovator", "pioneer", "postmaster", "1930", "macys", "marketing", "answer", "stores", "stores", "carolina", "massive", "remains", "general", "points", "company", "located"], "answers": ["F.\u00a0W. Woolworth Company [or Woolworth's]", "New York City [or NYC]", "John Wanamaker &lt;Cheyne&gt;"], "parts": ["This company, the pioneer of the five-and-dime store, was the namesake of a building that was the tallest in the world from 1913 to 1930. A 1960 sit-in in Greensboro, North Carolina, originated in one of its stores.", "The Woolworth Building was located in this city, which is also where Macy's department store was founded and where their flagship store remains to this day.", "This man was the namesake of a massive department store in Philadelphia that contains a twelve-story atrium and a huge organ. A marketing innovator, he also served as Benjamin Harrison's Postmaster General."], "subcategory": "American History", "category": "History"}, {"leadin": ["villagers", "don", "moved", "directed", "director", "audiences", "drinking", "strauss", "includes", "crazy", "opera", "dance", "enraged", "peter", "(reeshot)", "thought", "brook", "amina", "opera", "lover", "2009", "american", "audiences", "1949", "title", "opera", "character", "designs", "accused", "national", "composers", "prissy", "operas", "york", "drugs", "production", "veils", "setting", "points", "urinating", "featured", "phantom", "english", "10", "salvador", "giovanni", "dal\u00ed", "alps", "2001", "weird", "productions", "critics", "answer", "stage", "composer", "audience", "booed", "richard", "rodolfo", "count"], "answers": ["Wolfgang Amadeus Mozart", "Salome (SAH-lo-may)", "La sonnambula [or The Sleepwalker] (by Vincenzo Bellini) &lt;Cheyne&gt;"], "parts": ["A 2001 English National Opera production of an opera by this composer featured drinking, drugs, and urinating on stage. The director accused opera critics of being \"weird\" and \"prissy\" after the audience booed that production of this composer's Don Giovanni.", "A 1949 production of this Richard (REE-shot) Strauss opera directed by Peter Brook featured designs by Salvador Dal\u00ed and enraged audiences. This opera includes the \"Dance of the Seven Veils.\"", "American audiences booed a 2009 production of this opera that moved the setting from the Alps to New York. In this opera, the title character Amina is thought by villagers to be both a phantom and also the lover of Count Rodolfo."], "subcategory": "Other Fine Arts", "category": "Fine Arts"}, {"leadin": ["founded", "alfred", "manmade", "bierstadt", "1990", "movement", "rembrandt", "objects", "painting", "movement", "thompson", "artists", "paintings", "landscape", "john", "thomas", "light", "artists", "works", "gardner", "luminist", "american", "focus", "bricher", "fitz", "lane", "school", "painters", "museum", "grouped", "art", "baur", "identify", "henry", "lane", "artist", "points", "cole", "10", "included", "albert", "coined", "death", "stolen"], "answers": ["ships [or boats]", "Luminism", "Hudson River School &lt;Bentley&gt;"], "parts": ["Lane is best known for his paintings of these things. The only painting of one of these man-made objects by Rembrandt was stolen from the Gardner Museum in 1990.", "After his death, Lane was grouped into this American art movement, which gets its name from the painters' focus on light. John I. H. Baur coined the name of this movement and included artists such as Alfred Thompson Bricher in it.", "Several artists from this other school of American landscape artists, such as Albert Bierstadt, made Luminist works. This movement was founded by Thomas Cole."], "subcategory": "Visual Fine Arts", "category": "Fine Arts"}, {"leadin": ["siberian", "imf", "aimed", "published", "comparing", "bank", "1891", "clash", "dominoes", "advocated", "soviet", "noninvolvement", "root", "russias", "man", "cooperation", "lectured", "early", "telegram", "justified", "asia", "reasons", "idea", "doctrine", "civilizations", "originated", "southeast", "journal", "american", "explorer", "greatnephew", "huntingtons", "critique", "elihu", "union", "limit", "samuel", "surrounding", "stages", "supplement", "explained", "long", "telegram", "communism", "points", "war", "union", "buffer", "cold", "10", "pseudonym", "kennans", "included", "penal", "dubois", "contributors", "dressed", "journal", "america", "nations", "doctrine", "exile", "zone", "falling"], "answers": ["George F. Kennan [or George Frost Kennan]", "containment [or word forms]", "Foreign Affairs &lt;Shimizu&gt;"], "parts": ["Name this man who explained reasons for Soviet noninvolvement in the IMF and the World Bank in his Long Telegram, which advocated against American cooperation with the Soviet Union in the early stages of the Cold War.", "Kennan's Long Telegram originated this doctrine, which was justified in Southeast Asia by comparing its nations to falling dominoes. This doctrine aimed to limit Communism to a buffer zone surrounding the Soviet Union.", "This journal published the Long Telegram under Kennan's pseudonym \"X.\" This journal, whose early contributors included Elihu Root and W.\u00a0E.\u00a0B. DuBois, also originated Samuel Huntington's idea of the \"clash of civilizations.\""], "subcategory": "American History", "category": "History"}]}